nextx/__init__.py
nextx/controllers.py
nextx/dependencies/__init__.py
nextx/dependencies/utils.py
nextx/dependency_injection.py
nextx/domain/__init__.py
nextx/domain/commands.py
nextx/domain/events.py
nextx/domain/models.py
nextx/domain/viewmodels.py
nextx/exceptions/__init__.py
nextx/exceptions/definitions.py
nextx/exceptions/handlers.py
nextx/grpc/__init__.py
nextx/grpc/clients.py
nextx/grpc/protos/__init__.py
nextx/grpc/protos/blueprint.proto
nextx/grpc/protos/blueprint_grpc.py
nextx/grpc/protos/blueprint_pb2.py
nextx/grpc/protos/blueprint_pb2.pyi
nextx/interfaces/__init__.py
nextx/interfaces/iremotes.py
nextx/interfaces/irepository.py
nextx/interfaces/iuow.py
nextx/message_bus.py
nextx/pubsub/__init__.py
nextx/pubsub/isusbscriber.py
nextx/pubsub/redis.py
nextx/repository/__init__.py
nextx/repository/mongorepo.py
nextx/server.py
nextx/settings.py
nextx-0.15.0.dist-info/WHEEL
nextx-0.15.0.dist-info/METADATA
nextx-0.15.0.dist-info/RECORD
