Metadata-Version: 2.1
Name: nextx
Version: 0.15.0
Summary: Basic structure for fastapi microservices with specific support for blueprint project solution.
License: MIT
Author: adriangs1996
Author-email: adriangonzalezsanchez1996@gmail.com
Requires-Python: >=3.9,<4.0
Classifier: License :: OSI Approved :: MIT License
Classifier: Programming Language :: Python :: 3
Classifier: Programming Language :: Python :: 3.10
Classifier: Programming Language :: Python :: 3.9
Requires-Dist: Inject (>=4.3.1,<5.0.0)
Requires-Dist: aioredis (>=2.0.1,<3.0.0)
Requires-Dist: beanie (>=1.10.4,<2.0.0)
Requires-Dist: fastapi (>=0.75.1,<0.76.0)
Requires-Dist: grpclib (>=0.4.2,<0.5.0)
Requires-Dist: protobuf (>=3.20.0,<4.0.0)
Requires-Dist: python-decouple (>=3.6,<4.0)
Requires-Dist: python-jose (>=3.3.0,<4.0.0)
Requires-Dist: uvicorn (>=0.17.6,<0.18.0)
